C2Percentiles/__init__.py
C2Percentiles/percentiles.py
c2percentiles-0.1.1.dist-info/METADATA
c2percentiles-0.1.1.dist-info/WHEEL
c2percentiles-0.1.1.dist-info/licenses/LICENSE.txt
c2percentiles-0.1.1.dist-info/RECORD
