Metadata-Version: 2.4
Name: C2Percentiles
Version: 0.1.1
Summary: All nine Hyndman-Fan sample-quantile estimators plus pandas helpers & plots.
Author-email: Dr Subbiah <msubbiah@cepheus.in>
License: MIT
License-File: LICENSE.txt
Classifier: License :: OSI Approved :: MIT License
Classifier: Operating System :: OS Independent
Classifier: Programming Language :: Python :: 3
Requires-Python: >=3.8
Requires-Dist: numpy>=1.20
Requires-Dist: pandas>=1.3
Provides-Extra: plots
Requires-Dist: matplotlib>=3.3; extra == 'plots'
Requires-Dist: seaborn>=0.11; extra == 'plots'
